AUTHORS.rst
CONTRIBUTING.rst
HISTORY.rst
LICENSE
MANIFEST.in
README.rst
setup.cfg
setup.py
conctools/__init__.py
conctools/_geometry.py
conctools/_section_utils.py
conctools/_sectiongen.py
conctools/example1.py
conctools/sandbox.py
conctools/section.py
conctools.egg-info/PKG-INFO
conctools.egg-info/SOURCES.txt
conctools.egg-info/dependency_links.txt
conctools.egg-info/not-zip-safe
conctools.egg-info/top_level.txt
docs/Makefile
docs/authors.rst
docs/conf.py
docs/contributing.rst
docs/examples.rst
docs/explanations.rst
docs/history.rst
docs/index.rst
docs/installation.rst
docs/introduction.rst
docs/make.bat
docs/readme.rst
docs/section.rst
docs/_build/html/_static/file.png
docs/_build/html/_static/minus.png
docs/_build/html/_static/plus.png
tests/__init__.py
tests/test_geometry.py
tests/test_section.py
tests/test_section_utils.py
tests/test_sectiongen.py
tests/img/MN_unsym_section_desciption.txt
tests/img/Strain_diagram_equation.mcdx
tests/img/Untitled.mcdx
tests/img/compression_zone_split_draft.png
tests/img/strain_function.xlsx
tests/img/unsymmetrical_section.PNG
tests/img/Ref1_Example_4_10/FAGUS_setup.pdf
tests/img/Ref1_Example_4_10/Ref1_Example_4_10.xlsx
tests/img/Ref1_Example_4_10/Strain diagram_equation.PNG
tests/img/Ref1_Example_4_10/example_4_10_calc.py
tests/img/Ref1_Example_4_10/example_4_10_comparison.py
tests/img/Ref1_Example_4_10/ref1_example4_10_uniform compression_correction.mcdx
tests/img/Ref1_Example_4_10/FAGUS_ULS.FG6/preview.gra
tests/img/Ref1_Example_4_10/FAGUS_ULS.FG6/BAK/800X800.FGI
tests/img/Ref1_Example_4_10/FAGUS_ULS.FG6/BAK/FAGUS6.PRP
tests/img/Ref1_Example_4_10/FAGUS_ULS.FG6/INP/FAGUS6.prp
tests/img/Ref1_Example_4_10/FAGUS_ULS.FG6/INP/QB/800X800!118.FGI
tests/img/Ref1_Example_4_10/FAGUS_ULS.FG6/INP/QB/AnaParData.lst
tests/img/Ref1_Example_4_10/FAGUS_ULS.FG6/INP/QB/BstfData.lst
tests/img/Ref1_Example_4_10/FAGUS_ULS.FG6/INP/QB/QsData.lst