Metadata-Version: 2.1
Name: conctools
Version: 0.1.0
Summary: Tools for analysis of reinforced concrete sections
Home-page: https://github.com/timskovjacobsen/conctools
Author: Tim Skov Jacobsen
Author-email: timskovjacobsen@gmail.com
License: MIT license
Keywords: conctools
Platform: UNKNOWN
Classifier: Development Status :: 2 - Pre-Alpha
Classifier: Intended Audience :: Developers
Classifier: License :: OSI Approved :: MIT License
Classifier: Natural Language :: English
Classifier: Programming Language :: Python :: 3
Classifier: Programming Language :: Python :: 3.5
Classifier: Programming Language :: Python :: 3.6
Classifier: Programming Language :: Python :: 3.7
Classifier: Programming Language :: Python :: 3.8
Requires-Python: >=3.5
